{
  "_fv": 15,
  "_type": "food",
  "definition": {
    "renderType": 0,
    "texture": "moonsugar",
    "customModelName": "Normal",
    "name": "Moon Sugar",
    "rarity": "COMMON",
    "specialInfo": [],
    "creativeTab": {
      "value": "CUSTOM:ElderScrolls"
    },
    "stackSize": 1,
    "nutritionalValue": 0,
    "saturation": 0.0,
    "eatingSpeed": 16,
    "resultItem": {
      "value": "Items.BOWL"
    },
    "forDogs": false,
    "isAlwaysEdible": true,
    "animation": "eat",
    "hasGlow": false,
    "onEaten": {
      "name": "MoonSugarFoodEaten"
    }
  }
}